{
    "classes": [
        {
            "className": "ChatController",
            "lineNumber": 16,
            "methods": [
                {
                    "access": "public",
                    "arguments": [
                        {
                            "name": "text",
                            "type": "QString"
                        }
                    ],
                    "index": 2,
                    "lineNumber": 24,
                    "name": "sendMessage",
                    "returnType": "void"
                },
                {
                    "access": "public",
                    "arguments": [
                        {
                            "name": "text",
                            "type": "QString"
                        }
                    ],
                    "index": 3,
                    "lineNumber": 25,
                    "name": "clipText",
                    "returnType": "void"
                }
            ],
            "object": true,
            "properties": [
                {
                    "constant": false,
                    "designable": true,
                    "final": false,
                    "index": 0,
                    "lineNumber": 19,
                    "member": "_isLoading",
                    "name": "isLoading",
                    "notify": "isLoadingChanged",
                    "required": false,
                    "scriptable": true,
                    "stored": true,
                    "type": "bool",
                    "user": false
                },
                {
                    "constant": false,
                    "designable": true,
                    "final": false,
                    "index": 1,
                    "lineNumber": 20,
                    "member": "_responseData",
                    "name": "responseData",
                    "notify": "responseDataChanged",
                    "required": false,
                    "scriptable": true,
                    "stored": true,
                    "type": "QString",
                    "user": false
                }
            ],
            "qualifiedClassName": "ChatController",
            "signals": [
                {
                    "access": "public",
                    "index": 0,
                    "lineNumber": 19,
                    "name": "isLoadingChanged",
                    "returnType": "void"
                },
                {
                    "access": "public",
                    "index": 1,
                    "lineNumber": 20,
                    "name": "responseDataChanged",
                    "returnType": "void"
                }
            ],
            "superClasses": [
                {
                    "access": "public",
                    "name": "QObject"
                }
            ]
        }
    ],
    "inputFile": "ChatController.h",
    "outputRevision": 69
}
